odoo/addons/edi_component_oca/README.rst
odoo/addons/edi_component_oca/__init__.py
odoo/addons/edi_component_oca/__manifest__.py
odoo/addons/edi_component_oca/components/__init__.py
odoo/addons/edi_component_oca/components/base.py
odoo/addons/edi_component_oca/components/base_input.py
odoo/addons/edi_component_oca/components/base_output.py
odoo/addons/edi_component_oca/components/base_validate.py
odoo/addons/edi_component_oca/i18n/edi_component_oca.pot
odoo/addons/edi_component_oca/i18n/it.po
odoo/addons/edi_component_oca/models/__init__.py
odoo/addons/edi_component_oca/models/edi_backend.py
odoo/addons/edi_component_oca/models/edi_exchange_consumer_mixin.py
odoo/addons/edi_component_oca/models/edi_exchange_record.py
odoo/addons/edi_component_oca/models/edi_oca_component_handler.py
odoo/addons/edi_component_oca/readme/CONFIGURE.md
odoo/addons/edi_component_oca/readme/CONTRIBUTORS.md
odoo/addons/edi_component_oca/readme/DESCRIPTION.md
odoo/addons/edi_component_oca/static/description/icon.png
odoo/addons/edi_component_oca/static/description/index.html
odoo/addons/edi_component_oca/tests/__init__.py
odoo/addons/edi_component_oca/tests/common.py
odoo/addons/edi_component_oca/tests/fake_components.py
odoo/addons/edi_component_oca/tests/test_backend_base.py
odoo/addons/edi_component_oca/tests/test_backend_input.py
odoo/addons/edi_component_oca/tests/test_backend_output.py
odoo/addons/edi_component_oca/tests/test_backend_process.py
odoo/addons/edi_component_oca/tests/test_backend_validate.py
odoo/addons/edi_component_oca/tests/test_component_match.py
odoo/addons/edi_component_oca/tests/test_edi_backend_cron.py
odoo/addons/edi_component_oca/tests/test_edi_configuration.py
odoo/addons/edi_component_oca/tests/test_exchange_type_encoding.py
odoo/addons/edi_component_oca/tests/test_quick_exec.py
odoo_addon_edi_component_oca-18.0.1.0.1.2.dist-info/METADATA
odoo_addon_edi_component_oca-18.0.1.0.1.2.dist-info/WHEEL
odoo_addon_edi_component_oca-18.0.1.0.1.2.dist-info/top_level.txt
odoo_addon_edi_component_oca-18.0.1.0.1.2.dist-info/RECORD
